MANIFEST.in
README.rst
pyproject.toml
setup.cfg
setup.py
sarus/__init__.py
sarus/config.yaml
sarus/dataspec_wrapper.py
sarus/debug.py
sarus/sarus.py
sarus/serialization.py
sarus/typing.py
sarus/utils.py
sarus/wrapper_factory.py
sarus.egg-info/PKG-INFO
sarus.egg-info/SOURCES.txt
sarus.egg-info/dependency_links.txt
sarus.egg-info/not-zip-safe
sarus.egg-info/requires.txt
sarus.egg-info/top_level.txt
sarus/context/__init__.py
sarus/context/local_sdk.py
sarus/context/typing.py
sarus/federated_analytics/__init__.py
sarus/federated_analytics/lib.py
sarus/imblearn/__init__.py
sarus/imblearn/over_sampling.py
sarus/imblearn/pipeline.py
sarus/imblearn/under_sampling.py
sarus/legacy/__init__.py
sarus/legacy/tensorflow/__init__.py
sarus/legacy/tensorflow/dataset.py
sarus/legacy/tensorflow/model.py
sarus/llm/__init__.py
sarus/llm/pretrained.py
sarus/manager/__init__.py
sarus/manager/arrow_local.py
sarus/manager/arrow_remote.py
sarus/manager/base_remote.py
sarus/manager/cache_scalar_local.py
sarus/manager/dataspec_api.py
sarus/manager/parquet_local.py
sarus/manager/sdk_manager.py
sarus/manager/typing.py
sarus/manager/value_local.py
sarus/manager/value_remote.py
sarus/manager/ops/__init__.py
sarus/manager/ops/api.py
sarus/matplotlib/__init__.py
sarus/matplotlib/pyplot.py
sarus/numpy/__init__.py
sarus/numpy/random.py
sarus/numpy/scalars.py
sarus/optbinning/__init__.py
sarus/optbinning/binning.py
sarus/optbinning/scorecard.py
sarus/pandas/__init__.py
sarus/pandas/core.py
sarus/pandas/dataframe.py
sarus/pandas/io.py
sarus/pandas_profiling/__init__.py
sarus/pandas_profiling/profile_report.py
sarus/plotly/__init__.py
sarus/plotly/express.py
sarus/scipy/__init__.py
sarus/scipy/sparse.py
sarus/scripts/__init__.py
sarus/scripts/generate_op_list.py
sarus/shap/Explanation.py
sarus/shap/__init__.py
sarus/shap/explainers.py
sarus/shap/maskers.py
sarus/shap/plots.py
sarus/shap/utils.py
sarus/sklearn/__init__.py
sarus/sklearn/cluster.py
sarus/sklearn/compose.py
sarus/sklearn/decomposition.py
sarus/sklearn/ensemble.py
sarus/sklearn/impute.py
sarus/sklearn/inspection.py
sarus/sklearn/linear_model.py
sarus/sklearn/metrics.py
sarus/sklearn/model_selection.py
