Metadata-Version: 2.1
Name: sarus
Version: 0.9.6
Summary: Python client for the Sarus Gateway
Home-page: https://sarus.tech
Download-URL: 
Author: Sarus Technologies
Author-email: contact@sarus.tech
License: Apache License 2.0
Keywords: differential privacy,AI,Data privacy
Classifier: Programming Language :: Python :: 3
Classifier: Programming Language :: Python :: 3.7
Classifier: Programming Language :: Python :: 3.8
Classifier: Development Status :: 3 - Alpha
Classifier: Intended Audience :: Developers
Classifier: Topic :: Scientific/Engineering :: Artificial Intelligence
Classifier: License :: OSI Approved :: Apache Software License
Provides: sarus
Requires-Python: <3.11,>=3.7
Provides-Extra: sklearn
Provides-Extra: imblearn
Provides-Extra: tensorflow
Provides-Extra: pandas_profiling
Provides-Extra: plotly
Provides-Extra: xgboost
Provides-Extra: skopt
Provides-Extra: shap
Provides-Extra: optbinning
Provides-Extra: tests
